tmdb_cli/__init__.py
tmdb_cli/main.py
tmdb_cli_enhanced-2.0.0.dist-info/licenses/LICENSE
tmdb_cli_enhanced-2.0.0.dist-info/METADATA
tmdb_cli_enhanced-2.0.0.dist-info/WHEEL
tmdb_cli_enhanced-2.0.0.dist-info/entry_points.txt
tmdb_cli_enhanced-2.0.0.dist-info/top_level.txt
tmdb_cli_enhanced-2.0.0.dist-info/RECORD
