Metadata-Version: 2.4
Name: tmdb-cli-enhanced
Version: 2.0.0
Summary: A beautiful command-line interface for The Movie Database (TMDB) API with interactive features
Author-email: Hamza Danjaji <bhantsi@gmail.com>
Maintainer-email: Hamza Danjaji <bhantsi@gmail.com>
License-Expression: MIT
Project-URL: Homepage, https://github.com/hanzadj/tmdb-cli
Project-URL: Repository, https://github.com/hanzadj/tmdb-cli.git
Project-URL: Issues, https://github.com/hanzadj/tmdb-cli/issues
Project-URL: Documentation, https://github.com/hanzadj/tmdb-cli#readme
Keywords: tmdb,cli,movies,api,terminal,interactive,watchlist
Classifier: Development Status :: 5 - Production/Stable
Classifier: Environment :: Console
Classifier: Intended Audience :: End Users/Desktop
Classifier: Operating System :: OS Independent
Classifier: Programming Language :: Python :: 3
Classifier: Programming Language :: Python :: 3.8
Classifier: Programming Language :: Python :: 3.9
Classifier: Programming Language :: Python :: 3.10
Classifier: Programming Language :: Python :: 3.11
Classifier: Programming Language :: Python :: 3.12
Classifier: Topic :: Multimedia
Classifier: Topic :: Utilities
Classifier: Topic :: Internet :: WWW/HTTP :: Dynamic Content
Requires-Python: >=3.8
License-File: LICENSE
Requires-Dist: requests>=2.31.0
Requires-Dist: python-dotenv>=1.0.0
Requires-Dist: rich>=13.7.0
Requires-Dist: click>=8.1.7
Provides-Extra: dev
Requires-Dist: pytest>=7.0; extra == "dev"
Requires-Dist: black>=23.0; extra == "dev"
Requires-Dist: flake8>=6.0; extra == "dev"
Requires-Dist: mypy>=1.0; extra == "dev"
Dynamic: license-file
